{
  "bridges-city-01": {
    "hash": "f42fabb4d16cc0c6",
    "hud": {
      "tick": 43800,
      "population": 0,
      "fundsCents": 0
    }
  },
  "empty-city-01": {
    "hash": "9d2be848dc6be966",
    "hud": {
      "tick": 525600,
      "population": 0,
      "fundsCents": 0
    }
  },
  "growth-city-01": {
    "hash": "f642f43f8531827f",
    "hud": {
      "tick": 131400,
      "population": 649,
      "fundsCents": 0
    }
  },
  "road-grid-500-01": {
    "hash": "355c1ba9df138de9",
    "hud": {
      "tick": 43800,
      "population": 0,
      "fundsCents": 0
    }
  },
  "roads-city-01": {
    "hash": "18f681018df9012f",
    "hud": {
      "tick": 131400,
      "population": 0,
      "fundsCents": 0
    }
  }
}
